{
  "kind": "singleType",
  "collectionName": "profil_masjids",
  "info": {
    "singularName": "profil-masjid",
    "pluralName": "profil-masjids",
    "displayName": "profil_masjid"
  },
  "options": {
    "draftAndPublish": true
  },
  "pluginOptions": {},
  "attributes": {
    "Profil": {
      "type": "text"
    },
    "Judul": {
      "type": "string"
    },
    "gambar": {
      "type": "media",
      "multiple": false,
      "allowedTypes": [
        "images",
        "files",
        "videos",
        "audios"
      ]
    }
  }
}
